README.md
setup.py
bin/montage-mosaic
montage_mosaic/__init__.py
montage_mosaic/main.py
montage_mosaic/make_mosaic.py
montage_mosaic.egg-info/PKG-INFO
montage_mosaic.egg-info/SOURCES.txt
montage_mosaic.egg-info/dependency_links.txt
montage_mosaic.egg-info/requires.txt
montage_mosaic.egg-info/top_level.txt