Metadata-Version: 1.1
Name: montage-mosaic
Version: 0.0.2
Summary: A package with mosaicking commands from montage
Home-page: https://github.com/svw26
Author: Sarah White
Author-email: sarahwhite.astro@gmail.com
License: ['GNU GPL v2']
Platform: UNKNOWN
Classifier: Development Status :: 3 - Alpha
Classifier: Intended Audience :: Science/Research
Classifier: License :: OSI Approved :: GNU General Public License v2 (GPLv2)
Classifier: Operating System :: POSIX :: Linux
Classifier: Programming Language :: Python
Classifier: Topic :: Scientific/Engineering :: Astronomy
